pygenguard/__init__.py
pygenguard/decision.py
pygenguard/guard.py
pygenguard/session.py
pygenguard/audit/__init__.py
pygenguard/audit/logger.py
pygenguard/planes/__init__.py
pygenguard/planes/compliance.py
pygenguard/planes/context.py
pygenguard/planes/economics.py
pygenguard/planes/identity.py
pygenguard/planes/intent.py
pygenguard/utils/__init__.py
pygenguard/utils/hashing.py
pygenguard-0.1.0.dist-info/licenses/LICENSE
pygenguard-0.1.0.dist-info/METADATA
pygenguard-0.1.0.dist-info/WHEEL
pygenguard-0.1.0.dist-info/top_level.txt
pygenguard-0.1.0.dist-info/RECORD
