Metadata-Version: 2.4
Name: pygenguard
Version: 0.1.0
Summary: Runtime security and governance framework for GenAI systems
Author: PyGenGuard Contributors
License: Apache-2.0
Project-URL: Homepage, https://github.com/Jayasudhandesigner/pytrialguard
Project-URL: Documentation, https://github.com/Jayasudhandesigner/pytrialguard#readme
Project-URL: Repository, https://github.com/Jayasudhandesigner/pytrialguard
Project-URL: Issues, https://github.com/Jayasudhandesigner/pytrialguard/issues
Keywords: security,genai,llm,guardrails,trust,compliance,audit
Classifier: Development Status :: 4 - Beta
Classifier: Intended Audience :: Developers
Classifier: License :: OSI Approved :: Apache Software License
Classifier: Operating System :: OS Independent
Classifier: Programming Language :: Python :: 3
Classifier: Programming Language :: Python :: 3.9
Classifier: Programming Language :: Python :: 3.10
Classifier: Programming Language :: Python :: 3.11
Classifier: Programming Language :: Python :: 3.12
Classifier: Topic :: Security
Classifier: Topic :: Software Development :: Libraries :: Python Modules
Classifier: Typing :: Typed
Requires-Python: >=3.9
License-File: LICENSE
Provides-Extra: dev
Requires-Dist: pytest>=7.0; extra == "dev"
Requires-Dist: pytest-cov>=4.0; extra == "dev"
Requires-Dist: black>=23.0; extra == "dev"
Requires-Dist: mypy>=1.0; extra == "dev"
Requires-Dist: ruff>=0.1.0; extra == "dev"
Dynamic: license-file
